README.txt
setup.py
ckanext/__init__.py
ckanext/datapreview/__init__.py
ckanext_datapreview.egg-info/PKG-INFO
ckanext_datapreview.egg-info/SOURCES.txt
ckanext_datapreview.egg-info/dependency_links.txt
ckanext_datapreview.egg-info/entry_points.txt
ckanext_datapreview.egg-info/namespace_packages.txt
ckanext_datapreview.egg-info/not-zip-safe
ckanext_datapreview.egg-info/top_level.txt