Metadata-Version: 1.0
Name: ckanext-datapreview
Version: 0.1
Summary: CKAN Extension Data Preview - preview package resources.
Home-page: http://ckan.org/
Author: CKAN Team (Open Knowledge Foundation)
Author-email: ckan@okfn.org
License: mit
Platform: UNKNOWN
